pqapiv2/__init__.py
pqapiv2/api_helper.py
pqapiv2/configuration.py
pqapiv2/decorators.py
pqapiv2/pqapiv_2_client.py
pqapiv2/controllers/__init__.py
pqapiv2/controllers/balances_controller.py
pqapiv2/controllers/bank_accounts_controller.py
pqapiv2/controllers/base_controller.py
pqapiv2/controllers/documents_controller.py
pqapiv2/controllers/paper_checks_controller.py
pqapiv2/controllers/payments_controller.py
pqapiv2/controllers/prepaid_cards_controller.py
pqapiv2/controllers/program_controller.py
pqapiv2/controllers/receipts_controller.py
pqapiv2/controllers/spend_back_controller.py
pqapiv2/controllers/transfers_controller.py
pqapiv2/controllers/users_controller.py
pqapiv2/controllers/webhooks_controller.py
pqapiv2/exceptions/__init__.py
pqapiv2/exceptions/api_exception.py
pqapiv2/http/__init__.py
pqapiv2/http/http_call_back.py
pqapiv2/http/http_client.py
pqapiv2/http/http_method_enum.py
pqapiv2/http/http_request.py
pqapiv2/http/http_response.py
pqapiv2/http/requests_client.py
pqapiv2/models/__init__.py
pqapiv2/models/address.py
pqapiv2/models/address_types_enum.py
pqapiv2/models/auto_accept_quote.py
pqapiv2/models/balance.py
pqapiv2/models/balance_collection_response.py
pqapiv2/models/bank_account.py
pqapiv2/models/bank_account_collection_response.py
pqapiv2/models/bank_account_field_types_enum.py
pqapiv2/models/bank_account_fields.py
pqapiv2/models/bank_account_ownership.py
pqapiv2/models/bank_account_ownership_types_enum.py
pqapiv2/models/bank_account_required_fields.py
pqapiv2/models/bank_account_requirement.py
pqapiv2/models/bank_account_requirement_collection_response.py
pqapiv2/models/bank_account_requirement_format.py
pqapiv2/models/bank_account_requirement_format_legend.py
pqapiv2/models/bank_account_requirement_response.py
pqapiv2/models/bank_account_requirement_validator.py
pqapiv2/models/bank_account_response.py
pqapiv2/models/bank_account_status.py
pqapiv2/models/bank_account_status_types_enum.py
pqapiv2/models/bank_account_type.py
pqapiv_2-2021.6.17.dist-info/LICENSE
pqapiv_2-2021.6.17.dist-info/METADATA
pqapiv_2-2021.6.17.dist-info/WHEEL
pqapiv_2-2021.6.17.dist-info/top_level.txt
pqapiv_2-2021.6.17.dist-info/RECORD
