Metadata-Version: 2.1
Name: pqapiv-2
Version: 2021.6.17
Summary: desc
Home-page: https://www.payquicker.com
Author: PayQuicker Support
Author-email: support@payquicker.com
License: UNKNOWN
Platform: UNKNOWN
License-File: LICENSE
Requires-Dist: jsonpickle (>=1.4.1,~=1.4)
Requires-Dist: requests (~=2.25)
Requires-Dist: cachecontrol (~=0.12.6)
Requires-Dist: python-dateutil (~=2.8.1)
Requires-Dist: enum34 (>=1.1.10,~=1.1)
